sdprot/sdprotchk.py
sdprot/sdprotgen.py
sdprot/sdsysprot.py
sdprot-0.0.1.dist-info/METADATA
sdprot-0.0.1.dist-info/WHEEL
sdprot-0.0.1.dist-info/top_level.txt
sdprot-0.0.1.dist-info/RECORD
